redis_mcp/__init__.py
redis_mcp/__main__.py
redis_mcp/server.py
redis_mcp-0.1.3.dist-info/METADATA
redis_mcp-0.1.3.dist-info/WHEEL
redis_mcp-0.1.3.dist-info/entry_points.txt
redis_mcp-0.1.3.dist-info/RECORD
