Metadata-Version: 2.4
Name: redis-mcp
Version: 0.1.3
Summary: A FastMCP-based server with SSE support for Redis operations
Author: OAuthBringer
License: MIT
Requires-Python: >=3.10
Requires-Dist: fastmcp>=2.3.3
Requires-Dist: pydantic>=2.0.0
Requires-Dist: redis>=5.0.0
Provides-Extra: dev
Requires-Dist: black>=23.0.0; extra == 'dev'
Requires-Dist: fakeredis>=2.20.0; extra == 'dev'
Requires-Dist: isort>=5.12.0; extra == 'dev'
Requires-Dist: mypy>=1.0.0; extra == 'dev'
Requires-Dist: pytest-asyncio>=0.21.0; extra == 'dev'
Requires-Dist: pytest>=7.0.0; extra == 'dev'
Requires-Dist: ruff>=0.0.270; extra == 'dev'
